blnk_chat/__init__.py
blnk_chat/main.py
blnk_chat/apis/__init__.py
blnk_chat/apis/anthropic_api.py
blnk_chat/apis/base_api.py
blnk_chat/apis/echo_api.py
blnk_chat/apis/gemini_api.py
blnk_chat/apis/openai_api.py
blnk_chat/config/__init__.py
blnk_chat/config/blnk_mcp_config.json
blnk_chat/config/config.json
blnk_chat/config/models.py
blnk_chat/core/__init__.py
blnk_chat/core/chat_manager.py
blnk_chat/prompts/STYLE.md
blnk_chat/prompts/SYSTEM.md
blnk_chat/ui/__init__.py
blnk_chat/ui/colors.py
blnk_chat/ui/display.py
blnk_chat/utils/__init__.py
blnk_chat/utils/config_loader.py
blnk_chat/utils/mcp_client.py
blnk_chat/utils/mcp_formatter.py
blnk_chat/utils/setup_manager.py
blnk_chat/utils/version.py
blnk_chat-0.2.0.dist-info/METADATA
blnk_chat-0.2.0.dist-info/WHEEL
blnk_chat-0.2.0.dist-info/entry_points.txt
blnk_chat-0.2.0.dist-info/licenses/LICENSE
blnk_chat-0.2.0.dist-info/RECORD
