Metadata-Version: 2.4
Name: blnk-chat
Version: 0.2.0
Summary: A powerful terminal-based chat application for seamless interaction with multiple AI providers
Project-URL: Homepage, https://github.com/frgmt0/blnk
Project-URL: Repository, https://github.com/frgmt0/blnk
Project-URL: Documentation, https://github.com/frgmt0/blnk#readme
Project-URL: Bug Tracker, https://github.com/frgmt0/blnk/issues
Author-email: frgmt0_o <frgmt_@frgmt.xyz>
License-Expression: MIT
License-File: LICENSE
Keywords: ai,anthropic,chat,cli,gemini,openai
Classifier: Development Status :: 3 - Alpha
Classifier: Environment :: Console
Classifier: Intended Audience :: Developers
Classifier: License :: OSI Approved :: MIT License
Classifier: Programming Language :: Python :: 3
Classifier: Programming Language :: Python :: 3.13
Classifier: Topic :: Communications :: Chat
Classifier: Topic :: Scientific/Engineering :: Artificial Intelligence
Requires-Python: >=3.11
Requires-Dist: anthropic>=0.43.0
Requires-Dist: asyncio>=3.4.3
Requires-Dist: colorama>=0.4.6
Requires-Dist: google-generativeai>=0.3.0
Requires-Dist: mcp[cli]>=1.2.0
Requires-Dist: openai>=1.0.0
Requires-Dist: python-dotenv>=1.0.0
Requires-Dist: rich>=13.0.0
